{
  "updated": "2026-02-28T00:24:12.088005+00:00",
  "revenue": {
    "total": 0,
    "last_7d": 0
  },
  "strategies": [
    {
      "id": "crypto_trading",
      "name": "Crypto Trading",
      "type": "crypto_trading",
      "status": "active",
      "total_revenue": 834.7794485393817,
      "total_effort": 6204
    },
    {
      "id": "digital_products",
      "name": "Digital Product Factory",
      "type": "digital_products",
      "status": "active",
      "total_revenue": 0.0,
      "total_effort": 6728
    },
    {
      "id": "freelance",
      "name": "Freelance Scanner",
      "type": "freelance",
      "status": "active",
      "total_revenue": 0.0,
      "total_effort": 90
    },
    {
      "id": "micro_saas",
      "name": "Micro-SaaS Deployer",
      "type": "micro_saas",
      "status": "active",
      "total_revenue": 0.0,
      "total_effort": 1307
    },
    {
      "id": "seo_content",
      "name": "SEO Content Engine",
      "type": "seo_content",
      "status": "active",
      "total_revenue": 0.0,
      "total_effort": 29559
    },
    {
      "id": "social_growth",
      "name": "Social Growth Engine",
      "type": "social_growth",
      "status": "paused",
      "total_revenue": 0.0,
      "total_effort": 4190
    },
    {
      "id": "api_products",
      "name": "API Products",
      "type": "api_products",
      "status": "active",
      "total_revenue": 0.0,
      "total_effort": 10
    },
    {
      "id": "content_optimizer",
      "name": "Content Optimizer",
      "type": "content_optimizer",
      "status": "active",
      "total_revenue": 0.0,
      "total_effort": 2574
    },
    {
      "id": "data_scraper",
      "name": "Data Scraper",
      "type": "data_scraper",
      "status": "paused",
      "total_revenue": 0.0,
      "total_effort": 9695
    },
    {
      "id": "stripe_premium",
      "name": "Stripe Premium Tools",
      "type": "stripe_premium",
      "status": "active",
      "total_revenue": 0.0,
      "total_effort": 8769
    },
    {
      "id": "course_creator",
      "name": "Course Creator",
      "type": "course_creator",
      "status": "active",
      "total_revenue": 0.0,
      "total_effort": 84
    },
    {
      "id": "dropshipping",
      "name": "Dropshipping Store",
      "type": "dropshipping",
      "status": "active",
      "total_revenue": 0.0,
      "total_effort": 361
    },
    {
      "id": "shopify_store",
      "name": "Shopify Store (Trend)",
      "type": "shopify_store",
      "status": "active",
      "total_revenue": 0.0,
      "total_effort": 37188
    },
    {
      "id": "marketing_engine",
      "name": "Marketing Engine",
      "type": "marketing",
      "status": "active",
      "total_revenue": 0.0,
      "total_effort": 27067
    },
    {
      "id": "strategy_reviewer",
      "name": "Strategy Reviewer",
      "type": "strategy_reviewer",
      "status": "active",
      "total_revenue": 0.0,
      "total_effort": 3685
    },
    {
      "id": "solana_sniper",
      "name": "Solana Sniper",
      "type": "solana_sniper",
      "status": "active",
      "total_revenue": 0.0,
      "total_effort": 661
    }
  ],
  "actions_today": {
    "total": 248,
    "successes": 74
  },
  "recent_actions": [
    {
      "strategy_id": "data_scraper",
      "action_type": null,
      "outcome": "partial",
      "reward": 0.0,
      "executed_at": "2026-02-28 00:24:06"
    },
    {
      "strategy_id": "data_scraper",
      "action_type": "discover_communities",
      "outcome": null,
      "reward": 0.0,
      "executed_at": "2026-02-28 00:24:06"
    },
    {
      "strategy_id": "marketing_engine",
      "action_type": null,
      "outcome": "success",
      "reward": 0.3,
      "executed_at": "2026-02-28 00:23:02"
    },
    {
      "strategy_id": "marketing_engine",
      "action_type": "marketing_seo_optimize",
      "outcome": null,
      "reward": 0.0,
      "executed_at": "2026-02-28 00:23:02"
    },
    {
      "strategy_id": "data_scraper",
      "action_type": null,
      "outcome": "partial",
      "reward": 0.0,
      "executed_at": "2026-02-28 00:22:56"
    },
    {
      "strategy_id": "data_scraper",
      "action_type": "scrape_and_publish",
      "outcome": null,
      "reward": 0.0,
      "executed_at": "2026-02-28 00:22:56"
    },
    {
      "strategy_id": "social_growth",
      "action_type": null,
      "outcome": "success",
      "reward": 0.3,
      "executed_at": "2026-02-28 00:22:49"
    },
    {
      "strategy_id": "social_growth",
      "action_type": "send_promo_email",
      "outcome": null,
      "reward": 0.0,
      "executed_at": "2026-02-28 00:22:49"
    },
    {
      "strategy_id": "marketing_engine",
      "action_type": null,
      "outcome": "partial",
      "reward": 0.0,
      "executed_at": "2026-02-28 00:22:49"
    },
    {
      "strategy_id": "marketing_engine",
      "action_type": null,
      "outcome": "partial",
      "reward": 0.0,
      "executed_at": "2026-02-28 00:22:49"
    },
    {
      "strategy_id": "marketing_engine",
      "action_type": null,
      "outcome": "partial",
      "reward": 0.0,
      "executed_at": "2026-02-28 00:22:49"
    },
    {
      "strategy_id": "marketing_engine",
      "action_type": "marketing_promote_product",
      "outcome": null,
      "reward": 0.0,
      "executed_at": "2026-02-28 00:22:49"
    },
    {
      "strategy_id": "marketing_engine",
      "action_type": "marketing_promote_product",
      "outcome": null,
      "reward": 0.0,
      "executed_at": "2026-02-28 00:22:49"
    },
    {
      "strategy_id": "marketing_engine",
      "action_type": "marketing_promote_product",
      "outcome": null,
      "reward": 0.0,
      "executed_at": "2026-02-28 00:22:49"
    },
    {
      "strategy_id": "marketing_engine",
      "action_type": null,
      "outcome": "failure",
      "reward": 0.0,
      "executed_at": "2026-02-28 00:22:49"
    },
    {
      "strategy_id": "marketing_engine",
      "action_type": null,
      "outcome": "failure",
      "reward": 0.0,
      "executed_at": "2026-02-28 00:22:49"
    },
    {
      "strategy_id": "marketing_engine",
      "action_type": "marketing_welcome_new",
      "outcome": null,
      "reward": 0.0,
      "executed_at": "2026-02-28 00:22:49"
    },
    {
      "strategy_id": "marketing_engine",
      "action_type": "marketing_promote_product",
      "outcome": null,
      "reward": 0.0,
      "executed_at": "2026-02-28 00:22:49"
    },
    {
      "strategy_id": "marketing_engine",
      "action_type": null,
      "outcome": "partial",
      "reward": 0.0,
      "executed_at": "2026-02-28 00:22:49"
    },
    {
      "strategy_id": "marketing_engine",
      "action_type": null,
      "outcome": "partial",
      "reward": 0.0,
      "executed_at": "2026-02-28 00:22:49"
    },
    {
      "strategy_id": "marketing_engine",
      "action_type": null,
      "outcome": "partial",
      "reward": 0.0,
      "executed_at": "2026-02-28 00:22:49"
    },
    {
      "strategy_id": "marketing_engine",
      "action_type": "marketing_promote_product",
      "outcome": null,
      "reward": 0.0,
      "executed_at": "2026-02-28 00:22:49"
    },
    {
      "strategy_id": "marketing_engine",
      "action_type": "marketing_promote_product",
      "outcome": null,
      "reward": 0.0,
      "executed_at": "2026-02-28 00:22:49"
    },
    {
      "strategy_id": "marketing_engine",
      "action_type": "marketing_promote_product",
      "outcome": null,
      "reward": 0.0,
      "executed_at": "2026-02-28 00:22:49"
    },
    {
      "strategy_id": "marketing_engine",
      "action_type": null,
      "outcome": "failure",
      "reward": 0.0,
      "executed_at": "2026-02-28 00:22:49"
    },
    {
      "strategy_id": "marketing_engine",
      "action_type": null,
      "outcome": "failure",
      "reward": 0.0,
      "executed_at": "2026-02-28 00:22:49"
    },
    {
      "strategy_id": "marketing_engine",
      "action_type": "marketing_promote_product",
      "outcome": null,
      "reward": 0.0,
      "executed_at": "2026-02-28 00:22:49"
    },
    {
      "strategy_id": "marketing_engine",
      "action_type": "marketing_promote_product",
      "outcome": null,
      "reward": 0.0,
      "executed_at": "2026-02-28 00:22:49"
    },
    {
      "strategy_id": "solana_sniper",
      "action_type": "sync_metrics",
      "outcome": "success",
      "reward": 0.0,
      "executed_at": "2026-02-28 00:22:01"
    },
    {
      "strategy_id": "marketing_engine",
      "action_type": null,
      "outcome": "partial",
      "reward": 0.0,
      "executed_at": "2026-02-28 00:22:01"
    }
  ],
  "decisions": [
    {
      "decision_type": "allocate",
      "reasoning": "Round 73, C=1.040\n  content_optimizer: score=0.428 (mean=0.150, pulls=100) \u2192 762 tokens\n  course_creator: score=0.624 (mean=0.161, pulls=36) \u2192 888 tokens\n  crypto_trading: score=0.428 (mean=0.150, pulls=100) \u2192 762 tokens\n  data_scraper: score=0.278 (mean=0.000, pulls=100) \u2192 665 tokens\n  digital_products: score=0.419 (mean=0.141, pulls=100) \u2192 756 tokens\n  marketing_engine: score=0.293 (mean=0.015, pulls=100) \u2192 675 tokens\n  micro_saas: score=0.428 (mean=0.150, pulls=100) \u2192 762 tokens\n  seo_content: score=0.502 (mean=0.224, pulls=100) \u2192 809 tokens\n  shopify_store: score=0.425 (mean=0.147, pulls=100) \u2192 760 tokens\n  social_growth: score=0.315 (mean=0.037, pulls=100) \u2192 689 tokens\n  solana_sniper: score=0.377 (mean=0.099, pulls=100) \u2192 729 tokens\n  strategy_reviewer: score=0.383 (mean=0.105, pulls=100) \u2192 733 tokens\n  stripe_premium: score=0.431 (mean=0.153, pulls=100) \u2192 763 tokens",
      "outcome": null,
      "created_at": "2026-02-28 00:19:25"
    },
    {
      "decision_type": "allocate",
      "reasoning": "Round 72, C=1.046\n  content_optimizer: score=0.429 (mean=0.150, pulls=100) \u2192 769 tokens\n  course_creator: score=0.626 (mean=0.161, pulls=36) \u2192 897 tokens\n  crypto_trading: score=0.429 (mean=0.150, pulls=100) \u2192 769 tokens\n  data_scraper: score=0.279 (mean=0.000, pulls=100) \u2192 672 tokens\n  digital_products: score=0.420 (mean=0.141, pulls=100) \u2192 764 tokens\n  marketing_engine: score=0.294 (mean=0.015, pulls=100) \u2192 682 tokens\n  micro_saas: score=0.429 (mean=0.150, pulls=100) \u2192 769 tokens\n  seo_content: score=0.503 (mean=0.224, pulls=100) \u2192 817 tokens\n  shopify_store: score=0.426 (mean=0.147, pulls=100) \u2192 767 tokens\n  social_growth: score=0.316 (mean=0.037, pulls=100) \u2192 696 tokens\n  solana_sniper: score=0.378 (mean=0.099, pulls=100) \u2192 736 tokens\n  strategy_reviewer: score=0.381 (mean=0.102, pulls=100) \u2192 738 tokens\n  stripe_premium: score=0.432 (mean=0.153, pulls=100) \u2192 771 tokens",
      "outcome": null,
      "created_at": "2026-02-28 00:14:31"
    },
    {
      "decision_type": "allocate",
      "reasoning": "Round 71, C=1.051\n  content_optimizer: score=0.430 (mean=0.150, pulls=100) \u2192 775 tokens\n  course_creator: score=0.628 (mean=0.161, pulls=36) \u2192 903 tokens\n  crypto_trading: score=0.430 (mean=0.150, pulls=100) \u2192 775 tokens\n  data_scraper: score=0.280 (mean=0.000, pulls=100) \u2192 677 tokens\n  digital_products: score=0.422 (mean=0.141, pulls=100) \u2192 769 tokens\n  marketing_engine: score=0.295 (mean=0.015, pulls=100) \u2192 687 tokens\n  micro_saas: score=0.430 (mean=0.150, pulls=100) \u2192 775 tokens\n  seo_content: score=0.504 (mean=0.224, pulls=100) \u2192 823 tokens\n  shopify_store: score=0.427 (mean=0.147, pulls=100) \u2192 773 tokens\n  social_growth: score=0.317 (mean=0.037, pulls=100) \u2192 701 tokens\n  solana_sniper: score=0.379 (mean=0.099, pulls=100) \u2192 742 tokens\n  strategy_reviewer: score=0.379 (mean=0.099, pulls=100) \u2192 742 tokens\n  stripe_premium: score=0.430 (mean=0.150, pulls=100) \u2192 775 tokens",
      "outcome": null,
      "created_at": "2026-02-28 00:04:36"
    },
    {
      "decision_type": "allocate",
      "reasoning": "Round 70, C=1.056\n  content_optimizer: score=0.432 (mean=0.150, pulls=100) \u2192 347 tokens\n  course_creator: score=0.631 (mean=0.161, pulls=36) \u2192 404 tokens\n  crypto_trading: score=0.432 (mean=0.150, pulls=100) \u2192 347 tokens\n  data_scraper: score=0.282 (mean=0.000, pulls=100) \u2192 303 tokens\n  digital_products: score=0.423 (mean=0.141, pulls=100) \u2192 344 tokens\n  marketing_engine: score=0.294 (mean=0.012, pulls=100) \u2192 307 tokens\n  micro_saas: score=0.432 (mean=0.150, pulls=100) \u2192 347 tokens\n  seo_content: score=0.506 (mean=0.224, pulls=100) \u2192 368 tokens\n  shopify_store: score=0.429 (mean=0.147, pulls=100) \u2192 346 tokens\n  social_growth: score=0.319 (mean=0.037, pulls=100) \u2192 314 tokens\n  solana_sniper: score=0.381 (mean=0.099, pulls=100) \u2192 332 tokens\n  strategy_reviewer: score=0.381 (mean=0.099, pulls=100) \u2192 332 tokens\n  stripe_premium: score=0.435 (mean=0.153, pulls=100) \u2192 348 tokens",
      "outcome": null,
      "created_at": "2026-02-27 23:59:28"
    },
    {
      "decision_type": "allocate",
      "reasoning": "Round 69, C=1.061\n  content_optimizer: score=0.433 (mean=0.150, pulls=100) \u2192 353 tokens\n  course_creator: score=0.633 (mean=0.161, pulls=36) \u2192 411 tokens\n  crypto_trading: score=0.433 (mean=0.150, pulls=100) \u2192 353 tokens\n  data_scraper: score=0.283 (mean=0.000, pulls=100) \u2192 309 tokens\n  digital_products: score=0.425 (mean=0.141, pulls=100) \u2192 350 tokens\n  marketing_engine: score=0.295 (mean=0.012, pulls=100) \u2192 312 tokens\n  micro_saas: score=0.433 (mean=0.150, pulls=100) \u2192 353 tokens\n  seo_content: score=0.507 (mean=0.224, pulls=100) \u2192 374 tokens\n  shopify_store: score=0.430 (mean=0.147, pulls=100) \u2192 352 tokens\n  social_growth: score=0.323 (mean=0.040, pulls=100) \u2192 320 tokens\n  solana_sniper: score=0.382 (mean=0.099, pulls=100) \u2192 338 tokens\n  strategy_reviewer: score=0.382 (mean=0.099, pulls=100) \u2192 338 tokens\n  stripe_premium: score=0.436 (mean=0.153, pulls=100) \u2192 353 tokens",
      "outcome": null,
      "created_at": "2026-02-27 23:54:27"
    },
    {
      "decision_type": "allocate",
      "reasoning": "Round 68, C=1.067\n  content_optimizer: score=0.435 (mean=0.150, pulls=100) \u2192 359 tokens\n  course_creator: score=0.636 (mean=0.161, pulls=36) \u2192 419 tokens\n  crypto_trading: score=0.435 (mean=0.150, pulls=100) \u2192 359 tokens\n  data_scraper: score=0.285 (mean=0.000, pulls=100) \u2192 314 tokens\n  digital_products: score=0.426 (mean=0.141, pulls=100) \u2192 356 tokens\n  marketing_engine: score=0.297 (mean=0.012, pulls=100) \u2192 318 tokens\n  micro_saas: score=0.435 (mean=0.150, pulls=100) \u2192 359 tokens\n  seo_content: score=0.509 (mean=0.224, pulls=100) \u2192 381 tokens\n  shopify_store: score=0.432 (mean=0.147, pulls=100) \u2192 358 tokens\n  social_growth: score=0.325 (mean=0.040, pulls=100) \u2192 326 tokens\n  solana_sniper: score=0.384 (mean=0.099, pulls=100) \u2192 344 tokens\n  strategy_reviewer: score=0.384 (mean=0.099, pulls=100) \u2192 344 tokens\n  stripe_premium: score=0.435 (mean=0.150, pulls=100) \u2192 359 tokens",
      "outcome": null,
      "created_at": "2026-02-27 23:49:27"
    },
    {
      "decision_type": "allocate",
      "reasoning": "Round 67, C=1.072\n  content_optimizer: score=0.436 (mean=0.150, pulls=100) \u2192 364 tokens\n  course_creator: score=0.638 (mean=0.161, pulls=36) \u2192 424 tokens\n  crypto_trading: score=0.436 (mean=0.150, pulls=100) \u2192 364 tokens\n  data_scraper: score=0.286 (mean=0.000, pulls=100) \u2192 319 tokens\n  digital_products: score=0.428 (mean=0.141, pulls=100) \u2192 361 tokens\n  marketing_engine: score=0.298 (mean=0.012, pulls=100) \u2192 322 tokens\n  micro_saas: score=0.436 (mean=0.150, pulls=100) \u2192 364 tokens\n  seo_content: score=0.510 (mean=0.224, pulls=100) \u2192 386 tokens\n  shopify_store: score=0.433 (mean=0.147, pulls=100) \u2192 363 tokens\n  social_growth: score=0.326 (mean=0.040, pulls=100) \u2192 331 tokens\n  solana_sniper: score=0.385 (mean=0.099, pulls=100) \u2192 348 tokens\n  strategy_reviewer: score=0.385 (mean=0.099, pulls=100) \u2192 348 tokens\n  stripe_premium: score=0.436 (mean=0.150, pulls=100) \u2192 364 tokens",
      "outcome": null,
      "created_at": "2026-02-27 23:44:36"
    },
    {
      "decision_type": "allocate",
      "reasoning": "Round 66, C=1.077\n  content_optimizer: score=0.438 (mean=0.150, pulls=100) \u2192 371 tokens\n  course_creator: score=0.640 (mean=0.161, pulls=36) \u2192 433 tokens\n  crypto_trading: score=0.438 (mean=0.150, pulls=100) \u2192 371 tokens\n  data_scraper: score=0.288 (mean=0.000, pulls=100) \u2192 325 tokens\n  digital_products: score=0.429 (mean=0.141, pulls=100) \u2192 368 tokens\n  marketing_engine: score=0.300 (mean=0.012, pulls=100) \u2192 328 tokens\n  micro_saas: score=0.438 (mean=0.150, pulls=100) \u2192 371 tokens\n  seo_content: score=0.512 (mean=0.224, pulls=100) \u2192 393 tokens\n  shopify_store: score=0.435 (mean=0.147, pulls=100) \u2192 370 tokens\n  social_growth: score=0.328 (mean=0.040, pulls=100) \u2192 337 tokens\n  solana_sniper: score=0.387 (mean=0.099, pulls=100) \u2192 355 tokens\n  strategy_reviewer: score=0.387 (mean=0.099, pulls=100) \u2192 355 tokens\n  stripe_premium: score=0.441 (mean=0.153, pulls=100) \u2192 371 tokens",
      "outcome": null,
      "created_at": "2026-02-27 23:39:44"
    },
    {
      "decision_type": "allocate",
      "reasoning": "Round 65, C=1.083\n  content_optimizer: score=0.439 (mean=0.150, pulls=100) \u2192 377 tokens\n  course_creator: score=0.643 (mean=0.161, pulls=36) \u2192 440 tokens\n  crypto_trading: score=0.439 (mean=0.150, pulls=100) \u2192 377 tokens\n  data_scraper: score=0.289 (mean=0.000, pulls=100) \u2192 330 tokens\n  digital_products: score=0.430 (mean=0.141, pulls=100) \u2192 374 tokens\n  marketing_engine: score=0.301 (mean=0.012, pulls=100) \u2192 334 tokens\n  micro_saas: score=0.439 (mean=0.150, pulls=100) \u2192 377 tokens\n  seo_content: score=0.513 (mean=0.224, pulls=100) \u2192 400 tokens\n  shopify_store: score=0.436 (mean=0.147, pulls=100) \u2192 376 tokens\n  social_growth: score=0.329 (mean=0.040, pulls=100) \u2192 343 tokens\n  solana_sniper: score=0.388 (mean=0.099, pulls=100) \u2192 361 tokens\n  strategy_reviewer: score=0.388 (mean=0.099, pulls=100) \u2192 361 tokens\n  stripe_premium: score=0.442 (mean=0.153, pulls=100) \u2192 378 tokens",
      "outcome": null,
      "created_at": "2026-02-27 23:34:35"
    },
    {
      "decision_type": "allocate",
      "reasoning": "Round 64, C=1.088\n  content_optimizer: score=0.440 (mean=0.150, pulls=100) \u2192 383 tokens\n  course_creator: score=0.645 (mean=0.161, pulls=36) \u2192 447 tokens\n  crypto_trading: score=0.440 (mean=0.150, pulls=100) \u2192 383 tokens\n  data_scraper: score=0.290 (mean=0.000, pulls=100) \u2192 336 tokens\n  digital_products: score=0.432 (mean=0.141, pulls=100) \u2192 380 tokens\n  marketing_engine: score=0.302 (mean=0.012, pulls=100) \u2192 339 tokens\n  micro_saas: score=0.440 (mean=0.150, pulls=100) \u2192 383 tokens\n  seo_content: score=0.514 (mean=0.224, pulls=100) \u2192 406 tokens\n  shopify_store: score=0.437 (mean=0.147, pulls=100) \u2192 382 tokens\n  social_growth: score=0.330 (mean=0.040, pulls=100) \u2192 348 tokens\n  solana_sniper: score=0.389 (mean=0.099, pulls=100) \u2192 367 tokens\n  strategy_reviewer: score=0.389 (mean=0.099, pulls=100) \u2192 367 tokens\n  stripe_premium: score=0.443 (mean=0.153, pulls=100) \u2192 384 tokens",
      "outcome": null,
      "created_at": "2026-02-27 23:29:37"
    },
    {
      "decision_type": "allocate",
      "reasoning": "Round 63, C=1.094\n  content_optimizer: score=0.442 (mean=0.150, pulls=100) \u2192 389 tokens\n  course_creator: score=0.648 (mean=0.161, pulls=36) \u2192 455 tokens\n  crypto_trading: score=0.442 (mean=0.150, pulls=100) \u2192 389 tokens\n  data_scraper: score=0.292 (mean=0.000, pulls=100) \u2192 341 tokens\n  digital_products: score=0.433 (mean=0.141, pulls=100) \u2192 387 tokens\n  marketing_engine: score=0.304 (mean=0.012, pulls=100) \u2192 345 tokens\n  micro_saas: score=0.442 (mean=0.150, pulls=100) \u2192 389 tokens\n  seo_content: score=0.516 (mean=0.224, pulls=100) \u2192 413 tokens\n  shopify_store: score=0.439 (mean=0.147, pulls=100) \u2192 388 tokens\n  social_growth: score=0.332 (mean=0.040, pulls=100) \u2192 354 tokens\n  solana_sniper: score=0.391 (mean=0.099, pulls=100) \u2192 373 tokens\n  strategy_reviewer: score=0.391 (mean=0.099, pulls=100) \u2192 373 tokens\n  stripe_premium: score=0.445 (mean=0.153, pulls=100) \u2192 390 tokens",
      "outcome": null,
      "created_at": "2026-02-27 23:24:27"
    },
    {
      "decision_type": "allocate",
      "reasoning": "Round 62, C=1.099\n  content_optimizer: score=0.443 (mean=0.150, pulls=100) \u2192 395 tokens\n  course_creator: score=0.650 (mean=0.161, pulls=36) \u2192 461 tokens\n  crypto_trading: score=0.443 (mean=0.150, pulls=100) \u2192 395 tokens\n  data_scraper: score=0.293 (mean=0.000, pulls=100) \u2192 347 tokens\n  digital_products: score=0.435 (mean=0.141, pulls=100) \u2192 392 tokens\n  marketing_engine: score=0.305 (mean=0.012, pulls=100) \u2192 351 tokens\n  micro_saas: score=0.443 (mean=0.150, pulls=100) \u2192 395 tokens\n  seo_content: score=0.517 (mean=0.224, pulls=100) \u2192 419 tokens\n  shopify_store: score=0.437 (mean=0.144, pulls=100) \u2192 393 tokens\n  social_growth: score=0.333 (mean=0.040, pulls=100) \u2192 360 tokens\n  solana_sniper: score=0.392 (mean=0.099, pulls=100) \u2192 379 tokens\n  strategy_reviewer: score=0.392 (mean=0.099, pulls=100) \u2192 379 tokens\n  stripe_premium: score=0.446 (mean=0.153, pulls=100) \u2192 396 tokens",
      "outcome": null,
      "created_at": "2026-02-27 23:14:27"
    },
    {
      "decision_type": "allocate",
      "reasoning": "Round 61, C=1.105\n  content_optimizer: score=0.445 (mean=0.150, pulls=100) \u2192 400 tokens\n  course_creator: score=0.652 (mean=0.161, pulls=36) \u2192 467 tokens\n  crypto_trading: score=0.445 (mean=0.150, pulls=100) \u2192 400 tokens\n  data_scraper: score=0.295 (mean=0.000, pulls=100) \u2192 351 tokens\n  digital_products: score=0.436 (mean=0.141, pulls=100) \u2192 397 tokens\n  marketing_engine: score=0.307 (mean=0.012, pulls=100) \u2192 355 tokens\n  micro_saas: score=0.445 (mean=0.150, pulls=100) \u2192 400 tokens\n  seo_content: score=0.519 (mean=0.224, pulls=100) \u2192 424 tokens\n  shopify_store: score=0.439 (mean=0.144, pulls=100) \u2192 398 tokens\n  social_growth: score=0.335 (mean=0.040, pulls=100) \u2192 364 tokens\n  solana_sniper: score=0.394 (mean=0.099, pulls=100) \u2192 383 tokens\n  strategy_reviewer: score=0.394 (mean=0.099, pulls=100) \u2192 383 tokens\n  stripe_premium: score=0.448 (mean=0.153, pulls=100) \u2192 401 tokens",
      "outcome": null,
      "created_at": "2026-02-27 23:09:28"
    },
    {
      "decision_type": "allocate",
      "reasoning": "Round 60, C=1.110\n  content_optimizer: score=0.446 (mean=0.150, pulls=100) \u2192 408 tokens\n  course_creator: score=0.655 (mean=0.161, pulls=36) \u2192 477 tokens\n  crypto_trading: score=0.446 (mean=0.150, pulls=100) \u2192 408 tokens\n  data_scraper: score=0.296 (mean=0.000, pulls=100) \u2192 358 tokens\n  digital_products: score=0.438 (mean=0.141, pulls=100) \u2192 405 tokens\n  marketing_engine: score=0.308 (mean=0.012, pulls=100) \u2192 362 tokens\n  micro_saas: score=0.446 (mean=0.150, pulls=100) \u2192 408 tokens\n  seo_content: score=0.520 (mean=0.224, pulls=100) \u2192 432 tokens\n  shopify_store: score=0.440 (mean=0.144, pulls=100) \u2192 406 tokens\n  social_growth: score=0.336 (mean=0.040, pulls=100) \u2192 372 tokens\n  solana_sniper: score=0.395 (mean=0.099, pulls=100) \u2192 391 tokens\n  strategy_reviewer: score=0.395 (mean=0.099, pulls=100) \u2192 391 tokens\n  stripe_premium: score=0.446 (mean=0.150, pulls=100) \u2192 408 tokens",
      "outcome": null,
      "created_at": "2026-02-27 23:04:31"
    },
    {
      "decision_type": "allocate",
      "reasoning": "Round 59, C=1.116\n  content_optimizer: score=0.448 (mean=0.150, pulls=100) \u2192 413 tokens\n  course_creator: score=0.657 (mean=0.161, pulls=36) \u2192 483 tokens\n  crypto_trading: score=0.442 (mean=0.144, pulls=100) \u2192 411 tokens\n  data_scraper: score=0.298 (mean=0.000, pulls=100) \u2192 363 tokens\n  digital_products: score=0.439 (mean=0.141, pulls=100) \u2192 410 tokens\n  marketing_engine: score=0.310 (mean=0.012, pulls=100) \u2192 367 tokens\n  micro_saas: score=0.448 (mean=0.150, pulls=100) \u2192 413 tokens\n  seo_content: score=0.522 (mean=0.224, pulls=100) \u2192 438 tokens\n  shopify_store: score=0.442 (mean=0.144, pulls=100) \u2192 411 tokens\n  social_growth: score=0.338 (mean=0.040, pulls=100) \u2192 376 tokens\n  solana_sniper: score=0.397 (mean=0.099, pulls=100) \u2192 396 tokens\n  strategy_reviewer: score=0.397 (mean=0.099, pulls=100) \u2192 396 tokens\n  stripe_premium: score=0.451 (mean=0.153, pulls=100) \u2192 414 tokens",
      "outcome": null,
      "created_at": "2026-02-27 22:59:27"
    },
    {
      "decision_type": "allocate",
      "reasoning": "Round 58, C=1.122\n  content_optimizer: score=0.449 (mean=0.150, pulls=100) \u2192 418 tokens\n  course_creator: score=0.660 (mean=0.161, pulls=36) \u2192 489 tokens\n  crypto_trading: score=0.443 (mean=0.144, pulls=100) \u2192 416 tokens\n  data_scraper: score=0.299 (mean=0.000, pulls=100) \u2192 368 tokens\n  digital_products: score=0.441 (mean=0.141, pulls=100) \u2192 415 tokens\n  marketing_engine: score=0.311 (mean=0.012, pulls=100) \u2192 372 tokens\n  micro_saas: score=0.449 (mean=0.150, pulls=100) \u2192 418 tokens\n  seo_content: score=0.523 (mean=0.224, pulls=100) \u2192 443 tokens\n  shopify_store: score=0.443 (mean=0.144, pulls=100) \u2192 416 tokens\n  social_growth: score=0.342 (mean=0.043, pulls=100) \u2192 382 tokens\n  solana_sniper: score=0.398 (mean=0.099, pulls=100) \u2192 401 tokens\n  strategy_reviewer: score=0.398 (mean=0.099, pulls=100) \u2192 401 tokens\n  stripe_premium: score=0.452 (mean=0.153, pulls=100) \u2192 419 tokens",
      "outcome": null,
      "created_at": "2026-02-27 22:54:27"
    },
    {
      "decision_type": "allocate",
      "reasoning": "Round 57, C=1.127\n  content_optimizer: score=0.451 (mean=0.150, pulls=100) \u2192 424 tokens\n  course_creator: score=0.662 (mean=0.161, pulls=36) \u2192 496 tokens\n  crypto_trading: score=0.445 (mean=0.144, pulls=100) \u2192 422 tokens\n  data_scraper: score=0.301 (mean=0.000, pulls=100) \u2192 373 tokens\n  digital_products: score=0.442 (mean=0.141, pulls=100) \u2192 421 tokens\n  marketing_engine: score=0.313 (mean=0.012, pulls=100) \u2192 377 tokens\n  micro_saas: score=0.451 (mean=0.150, pulls=100) \u2192 424 tokens\n  seo_content: score=0.525 (mean=0.224, pulls=100) \u2192 449 tokens\n  shopify_store: score=0.445 (mean=0.144, pulls=100) \u2192 422 tokens\n  social_growth: score=0.344 (mean=0.043, pulls=100) \u2192 388 tokens\n  solana_sniper: score=0.400 (mean=0.099, pulls=100) \u2192 407 tokens\n  strategy_reviewer: score=0.400 (mean=0.099, pulls=100) \u2192 407 tokens\n  stripe_premium: score=0.451 (mean=0.150, pulls=100) \u2192 424 tokens",
      "outcome": null,
      "created_at": "2026-02-27 22:49:26"
    },
    {
      "decision_type": "allocate",
      "reasoning": "Round 56, C=1.133\n  content_optimizer: score=0.452 (mean=0.150, pulls=100) \u2192 431 tokens\n  course_creator: score=0.665 (mean=0.161, pulls=36) \u2192 504 tokens\n  crypto_trading: score=0.446 (mean=0.144, pulls=100) \u2192 429 tokens\n  data_scraper: score=0.302 (mean=0.000, pulls=100) \u2192 379 tokens\n  digital_products: score=0.444 (mean=0.141, pulls=100) \u2192 428 tokens\n  marketing_engine: score=0.314 (mean=0.012, pulls=100) \u2192 383 tokens\n  micro_saas: score=0.452 (mean=0.150, pulls=100) \u2192 431 tokens\n  seo_content: score=0.526 (mean=0.224, pulls=100) \u2192 456 tokens\n  shopify_store: score=0.446 (mean=0.144, pulls=100) \u2192 429 tokens\n  social_growth: score=0.345 (mean=0.043, pulls=100) \u2192 394 tokens\n  solana_sniper: score=0.401 (mean=0.099, pulls=100) \u2192 413 tokens\n  strategy_reviewer: score=0.401 (mean=0.099, pulls=100) \u2192 413 tokens\n  stripe_premium: score=0.455 (mean=0.153, pulls=100) \u2192 432 tokens",
      "outcome": null,
      "created_at": "2026-02-27 22:44:27"
    },
    {
      "decision_type": "allocate",
      "reasoning": "Round 55, C=1.139\n  content_optimizer: score=0.454 (mean=0.150, pulls=100) \u2192 436 tokens\n  course_creator: score=0.667 (mean=0.161, pulls=36) \u2192 510 tokens\n  crypto_trading: score=0.442 (mean=0.138, pulls=100) \u2192 432 tokens\n  data_scraper: score=0.304 (mean=0.000, pulls=100) \u2192 384 tokens\n  digital_products: score=0.445 (mean=0.141, pulls=100) \u2192 433 tokens\n  marketing_engine: score=0.316 (mean=0.012, pulls=100) \u2192 388 tokens\n  micro_saas: score=0.454 (mean=0.150, pulls=100) \u2192 436 tokens\n  seo_content: score=0.528 (mean=0.224, pulls=100) \u2192 462 tokens\n  shopify_store: score=0.448 (mean=0.144, pulls=100) \u2192 434 tokens\n  social_growth: score=0.352 (mean=0.048, pulls=100) \u2192 401 tokens\n  solana_sniper: score=0.403 (mean=0.099, pulls=100) \u2192 418 tokens\n  strategy_reviewer: score=0.403 (mean=0.099, pulls=100) \u2192 418 tokens\n  stripe_premium: score=0.457 (mean=0.153, pulls=100) \u2192 437 tokens",
      "outcome": null,
      "created_at": "2026-02-27 22:39:27"
    },
    {
      "decision_type": "allocate",
      "reasoning": "Round 54, C=1.144\n  content_optimizer: score=0.455 (mean=0.150, pulls=100) \u2192 443 tokens\n  course_creator: score=0.670 (mean=0.161, pulls=36) \u2192 518 tokens\n  crypto_trading: score=0.443 (mean=0.138, pulls=100) \u2192 439 tokens\n  data_scraper: score=0.305 (mean=0.000, pulls=100) \u2192 390 tokens\n  digital_products: score=0.447 (mean=0.141, pulls=100) \u2192 440 tokens\n  marketing_engine: score=0.317 (mean=0.012, pulls=100) \u2192 395 tokens\n  micro_saas: score=0.455 (mean=0.150, pulls=100) \u2192 443 tokens\n  seo_content: score=0.529 (mean=0.224, pulls=100) \u2192 469 tokens\n  shopify_store: score=0.452 (mean=0.147, pulls=100) \u2192 442 tokens\n  social_growth: score=0.353 (mean=0.048, pulls=100) \u2192 407 tokens\n  solana_sniper: score=0.407 (mean=0.102, pulls=100) \u2192 426 tokens\n  strategy_reviewer: score=0.404 (mean=0.099, pulls=100) \u2192 425 tokens\n  stripe_premium: score=0.455 (mean=0.150, pulls=100) \u2192 443 tokens",
      "outcome": null,
      "created_at": "2026-02-27 22:34:33"
    }
  ],
  "assets": {
    "total": 20043,
    "published": 19616
  },
  "recent_assets": [
    {
      "strategy_id": "shopify_store",
      "asset_type": "post",
      "title": "Elevate Your Everyday: Styling & Using Trend's Top Products",
      "status": "published",
      "url": "",
      "created_at": "2026-02-28 00:16:19"
    },
    {
      "strategy_id": "shopify_store",
      "asset_type": "post",
      "title": "Revolutionize Your Mobile Experience: Top Phone Accessories to Get in 2026",
      "status": "published",
      "url": "https://theartofsound.github.io/autohustle-content/blog/revolutionize-your-mobile-experience-top-phone-accessories-to-get-in-2026/",
      "created_at": "2026-02-28 00:15:32"
    },
    {
      "strategy_id": "shopify_store",
      "asset_type": "other",
      "title": "Audit 2026-02-28T00:00 - Score:100 Fixes:0",
      "status": "published",
      "url": null,
      "created_at": "2026-02-28 00:00:46"
    },
    {
      "strategy_id": "shopify_store",
      "asset_type": "post",
      "title": "Elevate Your Everyday: Styling & Using Trend's Top Products",
      "status": "published",
      "url": "",
      "created_at": "2026-02-27 23:55:04"
    },
    {
      "strategy_id": "shopify_store",
      "asset_type": "post",
      "title": "Top 5 Fitness Accessories You Need to Elevate Your Workout Routine",
      "status": "published",
      "url": "",
      "created_at": "2026-02-27 23:40:31"
    },
    {
      "strategy_id": "shopify_store",
      "asset_type": "post",
      "title": "Unlock the Future of Your Home: Top Smart Devices to Upgrade Your Space",
      "status": "published",
      "url": "https://theartofsound.github.io/autohustle-content/blog/unlock-the-future-of-your-home-top-smart-devices-to-upgrade-your-space/",
      "created_at": "2026-02-27 23:40:20"
    },
    {
      "strategy_id": "shopify_store",
      "asset_type": "other",
      "title": "Audit 2026-02-27T23:25 - Score:100 Fixes:0",
      "status": "published",
      "url": null,
      "created_at": "2026-02-27 23:25:29"
    },
    {
      "strategy_id": "shopify_store",
      "asset_type": "post",
      "title": "The Ultimate Gift Guide: Tech Gadgets, Fitness Finds & Home Decor Gems for Every Trendsetter",
      "status": "published",
      "url": "",
      "created_at": "2026-02-27 23:25:28"
    },
    {
      "strategy_id": "shopify_store",
      "asset_type": "post",
      "title": "Rev Up Your Ride: Unconventional Car Accessories to Elevate Your Driving Experience",
      "status": "published",
      "url": "https://theartofsound.github.io/autohustle-content/blog/rev-up-your-ride-unconventional-car-accessories-to-elevate-your-driving-experien/",
      "created_at": "2026-02-27 23:25:06"
    },
    {
      "strategy_id": "shopify_store",
      "asset_type": "post",
      "title": "Summer Vibes and Steals: Seasonal Deals on Power Tools, Accessories, and More",
      "status": "published",
      "url": "",
      "created_at": "2026-02-27 23:05:33"
    },
    {
      "strategy_id": "shopify_store",
      "asset_type": "post",
      "title": "How We Curate the Best Products for You: A Behind-the-Scenes Look at Trend",
      "status": "published",
      "url": "",
      "created_at": "2026-02-27 22:50:14"
    },
    {
      "strategy_id": "shopify_store",
      "asset_type": "post",
      "title": "Budget-Friendly Outdoor Essentials: Top 10 Gear Picks Under $50",
      "status": "published",
      "url": "https://theartofsound.github.io/autohustle-content/blog/budget-friendly-outdoor-essentials-top-10-gear-picks-under-50/",
      "created_at": "2026-02-27 22:50:11"
    },
    {
      "strategy_id": "shopify_store",
      "asset_type": "other",
      "title": "Audit 2026-02-27T22:45 - Score:100 Fixes:0",
      "status": "published",
      "url": null,
      "created_at": "2026-02-27 22:45:13"
    },
    {
      "strategy_id": "shopify_store",
      "asset_type": "post",
      "title": "Top 5 Car Accessories You Need for a Smarter Drive",
      "status": "published",
      "url": "",
      "created_at": "2026-02-27 22:35:20"
    },
    {
      "strategy_id": "shopify_store",
      "asset_type": "post",
      "title": "Level Up Your Self-Care: 5 Must-Have Wellness Gadgets for the Modern Hustler",
      "status": "published",
      "url": "",
      "created_at": "2026-02-27 22:20:01"
    },
    {
      "strategy_id": "shopify_store",
      "asset_type": "other",
      "title": "Audit 2026-02-27T22:10 - Score:100 Fixes:0",
      "status": "published",
      "url": null,
      "created_at": "2026-02-27 22:10:02"
    },
    {
      "strategy_id": "shopify_store",
      "asset_type": "post",
      "title": "How We Curate the Best Products for You: A Behind-the-Scenes Look at Trend",
      "status": "published",
      "url": "",
      "created_at": "2026-02-27 22:05:31"
    },
    {
      "strategy_id": "shopify_store",
      "asset_type": "post",
      "title": "Revamp Your Workspace Without Breaking the Bank: Expert Tips",
      "status": "published",
      "url": "https://theartofsound.github.io/autohustle-content/blog/revamp-your-workspace-without-breaking-the-bank-expert-tips/",
      "created_at": "2026-02-27 22:05:08"
    },
    {
      "strategy_id": "shopify_store",
      "asset_type": "post",
      "title": "How We Curate the Best Products for You: A Behind-the-Scenes Look at Trend",
      "status": "published",
      "url": "",
      "created_at": "2026-02-27 21:50:06"
    },
    {
      "strategy_id": "shopify_store",
      "asset_type": "post",
      "title": "Transform Your Kitchen on a Budget: 10 Clever Upgrades You Can Do Today",
      "status": "published",
      "url": "https://theartofsound.github.io/autohustle-content/blog/transform-your-kitchen-on-a-budget-10-clever-upgrades-you-can-do-today/",
      "created_at": "2026-02-27 21:50:04"
    }
  ],
  "crypto": {
    "portfolio": [
      {
        "id": 16,
        "strategy_id": "crypto_trading",
        "coin": "bitcoin",
        "quantity": 0.00598210971338196,
        "avg_buy_price": 67995.64639291944,
        "total_invested": 406.7574167547684,
        "exchange": "coinbase",
        "current_value": 404.23508177207253,
        "updated_at": "2026-02-22 14:26:16"
      },
      {
        "id": 60,
        "strategy_id": "crypto_trading",
        "coin": "kite",
        "quantity": 1141.8930762144325,
        "avg_buy_price": 0.251760991442679,
        "total_invested": 287.48413298927613,
        "exchange": "coinbase",
        "current_value": 290.1550306660873,
        "updated_at": "2026-02-22 20:29:34"
      },
      {
        "id": 70,
        "strategy_id": "crypto_trading",
        "coin": "arpa",
        "quantity": 17355.11822404712,
        "avg_buy_price": 0.010811969972795061,
        "total_invested": 187.64301711270582,
        "exchange": "coinbase",
        "current_value": 189.17078864211362,
        "updated_at": "2026-02-22 20:29:37"
      },
      {
        "id": 74,
        "strategy_id": "crypto_trading",
        "coin": "plu",
        "quantity": 952.4153279365063,
        "avg_buy_price": 0.14736339948098212,
        "total_invested": 140.35116044251797,
        "exchange": "coinbase",
        "current_value": 134.86201043580928,
        "updated_at": "2026-02-22 20:29:39"
      },
      {
        "id": 35,
        "strategy_id": "crypto_trading",
        "coin": "up",
        "quantity": 2757.0495110389365,
        "avg_buy_price": 0.0401795296802189,
        "total_invested": 110.77695265862197,
        "exchange": "coinbase",
        "current_value": 116.01374300843283,
        "updated_at": "2026-02-23 01:21:00"
      },
      {
        "id": 68,
        "strategy_id": "crypto_trading",
        "coin": "lrds",
        "quantity": 4722.0391365730375,
        "avg_buy_price": 0.02435166312401282,
        "total_invested": 114.98950631223097,
        "exchange": "coinbase",
        "current_value": 114.27620393827293,
        "updated_at": "2026-02-23 01:08:45"
      },
      {
        "id": 18,
        "strategy_id": "crypto_trading",
        "coin": "ripple",
        "quantity": 80.41870525522755,
        "avg_buy_price": 1.398515736059023,
        "total_invested": 112.46682477292818,
        "exchange": "coinbase",
        "current_value": 111.19494375640313,
        "updated_at": "2026-02-22 20:59:39"
      },
      {
        "id": 17,
        "strategy_id": "crypto_trading",
        "coin": "ethereum",
        "quantity": 0.03379378397652748,
        "avg_buy_price": 1970.3602240081343,
        "total_invested": 66.58592776607318,
        "exchange": "coinbase",
        "current_value": 65.89483731367069,
        "updated_at": "2026-02-22 13:57:19"
      },
      {
        "id": 20,
        "strategy_id": "crypto_trading",
        "coin": "litecoin",
        "quantity": 0.9834736527454983,
        "avg_buy_price": 54.64533205846063,
        "total_invested": 53.742244325024956,
        "exchange": "coinbase",
        "current_value": 53.20592461353146,
        "updated_at": "2026-02-22 12:52:51"
      },
      {
        "id": 75,
        "strategy_id": "crypto_trading",
        "coin": "agld",
        "quantity": 97.75579301119761,
        "avg_buy_price": 0.3716082840435733,
        "total_invested": 36.326862496209884,
        "exchange": "coinbase",
        "current_value": 35.79817140070057,
        "updated_at": "2026-02-23 01:23:49"
      },
      {
        "id": 65,
        "strategy_id": "crypto_trading",
        "coin": "fun1",
        "quantity": 830.3678580672079,
        "avg_buy_price": 0.042650529590490885,
        "total_invested": 35.415628901487985,
        "exchange": "coinbase",
        "current_value": 35.58126271817986,
        "updated_at": "2026-02-22 15:15:07"
      },
      {
        "id": 72,
        "strategy_id": "crypto_trading",
        "coin": "apr",
        "quantity": 305.26394204869996,
        "avg_buy_price": 0.10754182855619873,
        "total_invested": 32.82864252019068,
        "exchange": "coinbase",
        "current_value": 32.693768193415764,
        "updated_at": "2026-02-22 17:55:14"
      },
      {
        "id": 71,
        "strategy_id": "crypto_trading",
        "coin": "bnkr",
        "quantity": 36548.484542096354,
        "avg_buy_price": 0.0006555527956739173,
        "total_invested": 23.959461219216216,
        "exchange": "coinbase",
        "current_value": 24.041593131790982,
        "updated_at": "2026-02-22 17:28:51"
      },
      {
        "id": 15,
        "strategy_id": "crypto_trading",
        "coin": "snx",
        "quantity": 49.13714695280809,
        "avg_buy_price": 0.42755250290315633,
        "total_invested": 21.0087101651933,
        "exchange": "coinbase",
        "current_value": 20.932424601896244,
        "updated_at": "2026-02-22 09:11:06"
      },
      {
        "id": 69,
        "strategy_id": "crypto_trading",
        "coin": "flock",
        "quantity": 202.66804068542487,
        "avg_buy_price": 0.06414430196312107,
        "total_invested": 13.0,
        "exchange": "coinbase",
        "current_value": 12.95048779979865,
        "updated_at": "2026-02-22 16:06:19"
      },
      {
        "id": 73,
        "strategy_id": "crypto_trading",
        "coin": "swell",
        "quantity": 6551.019878049643,
        "avg_buy_price": 0.0015400229125452677,
        "total_invested": 10.088720712735956,
        "exchange": "coinbase",
        "current_value": 9.957550214635457,
        "updated_at": "2026-02-22 16:52:01"
      },
      {
        "id": 19,
        "strategy_id": "crypto_trading",
        "coin": "dimo",
        "quantity": 593.83186997683,
        "avg_buy_price": 0.011981784788462676,
        "total_invested": 7.115165666592728,
        "exchange": "coinbase",
        "current_value": 7.167550670620339,
        "updated_at": "2026-02-22 11:59:53"
      },
      {
        "id": 38,
        "strategy_id": "crypto_trading",
        "coin": "cow",
        "quantity": 19.57872150139685,
        "avg_buy_price": 0.23452878481296657,
        "total_invested": 4.591773761914103,
        "exchange": "coinbase",
        "current_value": 4.530516155423231,
        "updated_at": "2026-02-22 11:48:30"
      },
      {
        "id": 52,
        "strategy_id": "crypto_trading",
        "coin": "asm",
        "quantity": 442.1186505242348,
        "avg_buy_price": 0.008134380478979877,
        "total_invested": 3.596361320217262,
        "exchange": "coinbase",
        "current_value": 3.5369492041938786,
        "updated_at": "2026-02-22 13:43:51"
      },
      {
        "id": 14,
        "strategy_id": "crypto_trading",
        "coin": "vtho",
        "quantity": 5326.193171138264,
        "avg_buy_price": 0.000655,
        "total_invested": 3.488656527095563,
        "exchange": "coinbase",
        "current_value": 3.488656527095563,
        "updated_at": "2026-02-22 08:28:42"
      },
      {
        "id": 37,
        "strategy_id": "crypto_trading",
        "coin": "pepe",
        "quantity": 626881.4275709022,
        "avg_buy_price": 4.12e-06,
        "total_invested": 2.5827514815921173,
        "exchange": "coinbase",
        "current_value": 2.5827514815921173,
        "updated_at": "2026-02-22 11:29:37"
      },
      {
        "id": 61,
        "strategy_id": "crypto_trading",
        "coin": "cfg",
        "quantity": 10.537407797681771,
        "avg_buy_price": 0.0949,
        "total_invested": 1.0,
        "exchange": "coinbase",
        "current_value": 1.0,
        "updated_at": "2026-02-22 13:43:54"
      },
      {
        "id": 64,
        "strategy_id": "crypto_trading",
        "coin": "acs",
        "quantity": 4732.6076668244195,
        "avg_buy_price": 0.0002113,
        "total_invested": 1.0,
        "exchange": "coinbase",
        "current_value": 1.0,
        "updated_at": "2026-02-22 13:59:47"
      }
    ],
    "trades": [
      {
        "coin": "agld",
        "side": "buy",
        "quantity": 61.66,
        "price": 0.3662,
        "total": 22.850850704,
        "exchange": "coinbase",
        "executed_at": "2026-02-23 01:23:49"
      },
      {
        "coin": "up",
        "side": "buy",
        "quantity": 121.9,
        "price": 0.042078948,
        "total": 5.1909768463344,
        "exchange": "coinbase",
        "executed_at": "2026-02-23 01:21:00"
      },
      {
        "coin": "agld",
        "side": "sell",
        "quantity": 24.77,
        "price": 0.3612,
        "total": 8.946924000000001,
        "exchange": "coinbase",
        "executed_at": "2026-02-23 01:20:55"
      },
      {
        "coin": "prompt",
        "side": "sell",
        "quantity": 318.5,
        "price": 0.05386,
        "total": 17.15441,
        "exchange": "coinbase",
        "executed_at": "2026-02-23 01:20:53"
      },
      {
        "coin": "prompt",
        "side": "buy",
        "quantity": 318.5,
        "price": 0.05397,
        "total": 17.39571834,
        "exchange": "coinbase",
        "executed_at": "2026-02-23 01:17:53"
      },
      {
        "coin": "agld",
        "side": "buy",
        "quantity": 24.77,
        "price": 0.3664,
        "total": 9.184636736,
        "exchange": "coinbase",
        "executed_at": "2026-02-23 01:17:46"
      },
      {
        "coin": "up",
        "side": "sell",
        "quantity": 504.0,
        "price": 0.04185,
        "total": 20.8392912,
        "exchange": "coinbase",
        "executed_at": "2026-02-23 01:17:43"
      },
      {
        "coin": "up",
        "side": "buy",
        "quantity": 252.0,
        "price": 0.04215,
        "total": 10.7492616,
        "exchange": "coinbase",
        "executed_at": "2026-02-23 01:14:49"
      },
      {
        "coin": "agld",
        "side": "sell",
        "quantity": 52.45,
        "price": 0.3732,
        "total": 19.33944792,
        "exchange": "coinbase",
        "executed_at": "2026-02-23 01:14:45"
      },
      {
        "coin": "agld",
        "side": "buy",
        "quantity": 52.45,
        "price": 0.3701,
        "total": 19.64468594,
        "exchange": "coinbase",
        "executed_at": "2026-02-23 01:11:49"
      }
    ],
    "prices": [
      {
        "coin": "bitcoin",
        "price_usd": 65902.0,
        "price_change_24h": -2.1479317251770307,
        "recorded_at": "2026-02-28 00:19:36"
      },
      {
        "coin": "bitcoin",
        "price_usd": 65902.0,
        "price_change_24h": -2.1479317251770307,
        "recorded_at": "2026-02-28 00:19:36"
      },
      {
        "coin": "ethereum",
        "price_usd": 1931.85,
        "price_change_24h": -4.555246021918328,
        "recorded_at": "2026-02-28 00:19:36"
      },
      {
        "coin": "ethereum",
        "price_usd": 1931.85,
        "price_change_24h": -4.555246021918328,
        "recorded_at": "2026-02-28 00:19:36"
      },
      {
        "coin": "solana",
        "price_usd": 81.93,
        "price_change_24h": -4.5383696293074305,
        "recorded_at": "2026-02-28 00:19:36"
      },
      {
        "coin": "solana",
        "price_usd": 81.93,
        "price_change_24h": -4.5383696293074305,
        "recorded_at": "2026-02-28 00:19:36"
      },
      {
        "coin": "dogecoin",
        "price_usd": 0.093555,
        "price_change_24h": -3.304711153000628,
        "recorded_at": "2026-02-28 00:19:36"
      },
      {
        "coin": "dogecoin",
        "price_usd": 0.093555,
        "price_change_24h": -3.304711153000628,
        "recorded_at": "2026-02-28 00:19:36"
      },
      {
        "coin": "cardano",
        "price_usd": 0.277848,
        "price_change_24h": -2.935841281224608,
        "recorded_at": "2026-02-28 00:19:36"
      },
      {
        "coin": "cardano",
        "price_usd": 0.277848,
        "price_change_24h": -2.935841281224608,
        "recorded_at": "2026-02-28 00:19:36"
      },
      {
        "coin": "polkadot",
        "price_usd": 1.6,
        "price_change_24h": -0.5212251628277719,
        "recorded_at": "2026-02-28 00:19:36"
      },
      {
        "coin": "polkadot",
        "price_usd": 1.6,
        "price_change_24h": -0.5212251628277719,
        "recorded_at": "2026-02-28 00:19:36"
      },
      {
        "coin": "chainlink",
        "price_usd": 8.71,
        "price_change_24h": -3.955154883193765,
        "recorded_at": "2026-02-28 00:19:36"
      },
      {
        "coin": "chainlink",
        "price_usd": 8.71,
        "price_change_24h": -3.955154883193765,
        "recorded_at": "2026-02-28 00:19:36"
      },
      {
        "coin": "litecoin",
        "price_usd": 54.65,
        "price_change_24h": -1.6822556801016957,
        "recorded_at": "2026-02-28 00:19:36"
      },
      {
        "coin": "litecoin",
        "price_usd": 54.65,
        "price_change_24h": -1.6822556801016957,
        "recorded_at": "2026-02-28 00:19:36"
      },
      {
        "coin": "ripple",
        "price_usd": 1.36,
        "price_change_24h": -2.894341679986468,
        "recorded_at": "2026-02-28 00:19:36"
      },
      {
        "coin": "ripple",
        "price_usd": 1.36,
        "price_change_24h": -2.894341679986468,
        "recorded_at": "2026-02-28 00:19:36"
      },
      {
        "coin": "shiba-inu",
        "price_usd": 5.79e-06,
        "price_change_24h": -2.9983597104800372,
        "recorded_at": "2026-02-28 00:19:36"
      },
      {
        "coin": "shiba-inu",
        "price_usd": 5.79e-06,
        "price_change_24h": -2.9983597104800372,
        "recorded_at": "2026-02-28 00:19:36"
      },
      {
        "coin": "pepe",
        "price_usd": 3.68e-06,
        "price_change_24h": -3.905093683070851,
        "recorded_at": "2026-02-28 00:19:36"
      },
      {
        "coin": "pepe",
        "price_usd": 3.68e-06,
        "price_change_24h": -3.905093683070851,
        "recorded_at": "2026-02-28 00:19:36"
      },
      {
        "coin": "sui",
        "price_usd": 0.901842,
        "price_change_24h": -3.5851921475658264,
        "recorded_at": "2026-02-28 00:19:36"
      },
      {
        "coin": "sui",
        "price_usd": 0.901842,
        "price_change_24h": -3.5851921475658264,
        "recorded_at": "2026-02-28 00:19:36"
      },
      {
        "coin": "bitcoin",
        "price_usd": 65993.0,
        "price_change_24h": -2.013254305837755,
        "recorded_at": "2026-02-28 00:14:45"
      },
      {
        "coin": "bitcoin",
        "price_usd": 65993.0,
        "price_change_24h": -2.013254305837755,
        "recorded_at": "2026-02-28 00:14:45"
      },
      {
        "coin": "ethereum",
        "price_usd": 1935.68,
        "price_change_24h": -4.442318419208736,
        "recorded_at": "2026-02-28 00:14:45"
      },
      {
        "coin": "ethereum",
        "price_usd": 1935.68,
        "price_change_24h": -4.442318419208736,
        "recorded_at": "2026-02-28 00:14:45"
      },
      {
        "coin": "solana",
        "price_usd": 82.03,
        "price_change_24h": -4.421332149191499,
        "recorded_at": "2026-02-28 00:14:45"
      },
      {
        "coin": "solana",
        "price_usd": 82.03,
        "price_change_24h": -4.421332149191499,
        "recorded_at": "2026-02-28 00:14:45"
      },
      {
        "coin": "dogecoin",
        "price_usd": 0.093597,
        "price_change_24h": -3.39469183882572,
        "recorded_at": "2026-02-28 00:14:45"
      },
      {
        "coin": "dogecoin",
        "price_usd": 0.093597,
        "price_change_24h": -3.39469183882572,
        "recorded_at": "2026-02-28 00:14:45"
      },
      {
        "coin": "cardano",
        "price_usd": 0.277752,
        "price_change_24h": -3.0334921132541313,
        "recorded_at": "2026-02-28 00:14:45"
      },
      {
        "coin": "cardano",
        "price_usd": 0.277752,
        "price_change_24h": -3.0334921132541313,
        "recorded_at": "2026-02-28 00:14:45"
      },
      {
        "coin": "polkadot",
        "price_usd": 1.6,
        "price_change_24h": -0.25660265870237786,
        "recorded_at": "2026-02-28 00:14:45"
      },
      {
        "coin": "polkadot",
        "price_usd": 1.6,
        "price_change_24h": -0.25660265870237786,
        "recorded_at": "2026-02-28 00:14:45"
      },
      {
        "coin": "chainlink",
        "price_usd": 8.72,
        "price_change_24h": -3.982710650196153,
        "recorded_at": "2026-02-28 00:14:45"
      },
      {
        "coin": "chainlink",
        "price_usd": 8.72,
        "price_change_24h": -3.982710650196153,
        "recorded_at": "2026-02-28 00:14:45"
      },
      {
        "coin": "litecoin",
        "price_usd": 54.66,
        "price_change_24h": -1.7128167731067776,
        "recorded_at": "2026-02-28 00:14:45"
      },
      {
        "coin": "litecoin",
        "price_usd": 54.66,
        "price_change_24h": -1.7128167731067776,
        "recorded_at": "2026-02-28 00:14:45"
      },
      {
        "coin": "ripple",
        "price_usd": 1.36,
        "price_change_24h": -2.890184414813782,
        "recorded_at": "2026-02-28 00:14:45"
      },
      {
        "coin": "ripple",
        "price_usd": 1.36,
        "price_change_24h": -2.890184414813782,
        "recorded_at": "2026-02-28 00:14:45"
      },
      {
        "coin": "shiba-inu",
        "price_usd": 5.79e-06,
        "price_change_24h": -2.9866101324222027,
        "recorded_at": "2026-02-28 00:14:45"
      },
      {
        "coin": "shiba-inu",
        "price_usd": 5.79e-06,
        "price_change_24h": -2.9866101324222027,
        "recorded_at": "2026-02-28 00:14:45"
      },
      {
        "coin": "pepe",
        "price_usd": 3.68e-06,
        "price_change_24h": -3.9068030858007274,
        "recorded_at": "2026-02-28 00:14:45"
      },
      {
        "coin": "pepe",
        "price_usd": 3.68e-06,
        "price_change_24h": -3.9068030858007274,
        "recorded_at": "2026-02-28 00:14:45"
      },
      {
        "coin": "sui",
        "price_usd": 0.901943,
        "price_change_24h": -3.562575020890059,
        "recorded_at": "2026-02-28 00:14:45"
      },
      {
        "coin": "sui",
        "price_usd": 0.901943,
        "price_change_24h": -3.562575020890059,
        "recorded_at": "2026-02-28 00:14:45"
      },
      {
        "coin": "sui",
        "price_usd": 0.900843,
        "price_change_24h": -3.838141415190937,
        "recorded_at": "2026-02-28 00:06:41"
      },
      {
        "coin": "pepe",
        "price_usd": 3.68e-06,
        "price_change_24h": -3.804326064743404,
        "recorded_at": "2026-02-28 00:06:40"
      },
      {
        "coin": "sui",
        "price_usd": 0.900843,
        "price_change_24h": -3.838141415190937,
        "recorded_at": "2026-02-28 00:06:40"
      },
      {
        "coin": "litecoin",
        "price_usd": 54.59,
        "price_change_24h": -1.9341387785808468,
        "recorded_at": "2026-02-28 00:06:39"
      },
      {
        "coin": "litecoin",
        "price_usd": 54.59,
        "price_change_24h": -1.9341387785808468,
        "recorded_at": "2026-02-28 00:06:39"
      },
      {
        "coin": "ripple",
        "price_usd": 1.36,
        "price_change_24h": -3.299623464264906,
        "recorded_at": "2026-02-28 00:06:39"
      },
      {
        "coin": "ripple",
        "price_usd": 1.36,
        "price_change_24h": -3.299623464264906,
        "recorded_at": "2026-02-28 00:06:39"
      },
      {
        "coin": "shiba-inu",
        "price_usd": 5.78e-06,
        "price_change_24h": -3.097723698503911,
        "recorded_at": "2026-02-28 00:06:39"
      },
      {
        "coin": "shiba-inu",
        "price_usd": 5.78e-06,
        "price_change_24h": -3.097723698503911,
        "recorded_at": "2026-02-28 00:06:39"
      },
      {
        "coin": "pepe",
        "price_usd": 3.68e-06,
        "price_change_24h": -3.804326064743404,
        "recorded_at": "2026-02-28 00:06:39"
      },
      {
        "coin": "polkadot",
        "price_usd": 1.6,
        "price_change_24h": -1.273599001026222,
        "recorded_at": "2026-02-28 00:06:38"
      },
      {
        "coin": "polkadot",
        "price_usd": 1.6,
        "price_change_24h": -1.273599001026222,
        "recorded_at": "2026-02-28 00:06:38"
      },
      {
        "coin": "chainlink",
        "price_usd": 8.71,
        "price_change_24h": -4.234815823704703,
        "recorded_at": "2026-02-28 00:06:38"
      },
      {
        "coin": "chainlink",
        "price_usd": 8.71,
        "price_change_24h": -4.234815823704703,
        "recorded_at": "2026-02-28 00:06:38"
      },
      {
        "coin": "cardano",
        "price_usd": 0.277469,
        "price_change_24h": -3.243437533927355,
        "recorded_at": "2026-02-28 00:06:37"
      },
      {
        "coin": "cardano",
        "price_usd": 0.277469,
        "price_change_24h": -3.243437533927355,
        "recorded_at": "2026-02-28 00:06:37"
      },
      {
        "coin": "solana",
        "price_usd": 81.89,
        "price_change_24h": -4.754182356426524,
        "recorded_at": "2026-02-28 00:06:36"
      },
      {
        "coin": "solana",
        "price_usd": 81.89,
        "price_change_24h": -4.754182356426524,
        "recorded_at": "2026-02-28 00:06:36"
      },
      {
        "coin": "dogecoin",
        "price_usd": 0.093386,
        "price_change_24h": -3.6529297498633984,
        "recorded_at": "2026-02-28 00:06:36"
      },
      {
        "coin": "dogecoin",
        "price_usd": 0.093386,
        "price_change_24h": -3.6529297498633984,
        "recorded_at": "2026-02-28 00:06:36"
      },
      {
        "coin": "ethereum",
        "price_usd": 1930.25,
        "price_change_24h": -4.6826621770240004,
        "recorded_at": "2026-02-28 00:06:35"
      },
      {
        "coin": "ethereum",
        "price_usd": 1930.25,
        "price_change_24h": -4.6826621770240004,
        "recorded_at": "2026-02-28 00:06:35"
      },
      {
        "coin": "bitcoin",
        "price_usd": 65894.0,
        "price_change_24h": -2.28588249353527,
        "recorded_at": "2026-02-28 00:06:34"
      },
      {
        "coin": "bitcoin",
        "price_usd": 65894.0,
        "price_change_24h": -2.28588249353527,
        "recorded_at": "2026-02-28 00:06:34"
      }
    ]
  }
}